utils/__init__.py
microblox-0.0.1.dist-info/LICENSE
microblox-0.0.1.dist-info/METADATA
microblox-0.0.1.dist-info/WHEEL
microblox-0.0.1.dist-info/top_level.txt
microblox-0.0.1.dist-info/RECORD
