Metadata-Version: 2.1
Name: microblox
Version: 0.0.1
Summary: Building blocks for pika driven micro services
Home-page: https://github.com/BayerischKongo/microblox
Author: BayerischKongo
Author-email: mail@kwijybo.de
License: UNKNOWN
Platform: UNKNOWN
Classifier: Programming Language :: Python :: 3
Classifier: License :: OSI Approved :: MIT License
Classifier: Operating System :: OS Independent
Requires-Python: >=3.6
